<?xml version="1.0" encoding="UTF-8"?><i><chatserver>chat.bilibili.com</chatserver><chatid>38070317</chatid><mission>0</mission><maxlimit>500</maxlimit><state>0</state><real_name>0</real_name><source>e-r</source><d p="47.26500,1,25,16777215,1525312002,0,c109dac8,4506867120">消灭零弹幕！！！</d><d p="41.06500,1,25,16777215,1525330821,0,e6c9eb32,4507338632">阿噗加油</d><d p="1.09100,1,25,16777215,1525331106,0,4ff12503,4507344193">承包弹幕</d><d p="8.33100,1,25,16777215,1525334535,0,cc4a070d,4507412891">真·新人</d><d p="3.46500,1,25,16777215,1525352136,0,c080f88a,4508129435">标准开头</d><d p="25.84800,1,25,16777215,1525360179,0,5681d578,4508524809">前排，沙发</d><d p="1.97700,1,25,16777215,1525370197,0,74bac210,4508855023">交封不杀！</d><d p="22.12700,1,25,16777215,1525395706,0,37a54cd3,4509070277">双压</d><d p="28.67400,1,25,16777215,1525395713,0,37a54cd3,4509070357">3压</d><d p="34.30400,1,25,16777215,1525395718,0,37a54cd3,4509070431">4压</d><d p="33.45000,5,25,16777215,1525399029,0,e8d97c0f,4509121323">火钳刘明</d><d p="38.48400,1,25,16777215,1525408058,0,2625d28b,4509345354">看到我，你们已经是100之后了</d><d p="38.38100,1,25,16777215,1525410374,0,fa58f868,4509452385">四压</d><d p="47.55800,1,25,16777215,1525410403,0,fa58f868,4509453708">格局双鸭</d><d p="16.66200,1,25,16777215,1525429493,0,9b1a2e86,4510045289">霸占空屏</d><d p="1.70100,1,25,16777215,1525430691,0,2d5396cc,4510100473">可带劲了</d><d p="9.00500,1,25,16777215,1525430725,0,2d5396cc,4510102068">可带劲啦！</d><d p="50.52300,1,25,16777215,1525434454,0,33708a9c,4510277090">前苏联诗人 简 拉基 茨德 rap</d><d p="38.42500,1,25,16777215,1525436934,0,3f18b179,4510402971">好厉害</d><d p="35.19500,1,25,16777215,1525436935,0,ee664520,4510403021">这个音乐很带劲儿</d><d p="43.36900,1,25,16777215,1525445471,0,13be24fd,4510865811">不错 加油</d><d p="35.44400,1,25,16777215,1525452739,0,36ae477f,4511328159">很多很多</d><d p="23.01500,1,25,16777215,1525452883,0,1eeea039,4511333653">妙</d><d p="42.15400,5,25,15138834,1525480224,0,96784945,4511693201">简.拉基.茨德</d><d p="43.94600,5,25,16707842,1525480249,0,96784945,4511693738">简.拉基.茨德</d><d p="0.31800,1,25,16777215,1525480327,0,8434a0ac,4511695535">火前留名</d><d p="11.00000,1,25,16777215,1525481070,0,5ee6aa9a,4511712951">火钳刘明</d><d p="30.00000,1,25,16777215,1525481090,0,5ee6aa9a,4511713465">填词不错</d><d p="32.64400,1,25,16777215,1525487184,0,5f383e8a,4511905155">👏👏👏👏👏👏👏👏👏👏👏👏</d><d p="39.04400,1,25,16777215,1525494559,0,1c7bc18e,4512220715">厉害了</d><d p="5.56500,1,25,16777215,1525497223,0,f8988409,4512363770">火钳刘明</d><d p="57.27900,1,25,16777215,1525498335,0,ec5d900c,4512421397">非常的洋气</d><d p="49.81200,1,25,16777215,1525499202,0,c21d7c19,4512464654">很多很多、、、、、、、</d><d p="59.13500,5,25,16711680,1525499240,0,c21d7c19,4512466532">可带精了！</d><d p="59.13500,5,25,10092288,1525499246,0,c21d7c19,4512466817">可带精了！</d><d p="43.59200,1,25,16777215,1525499251,0,df9f0960,4512467109">👏👏👏👏👏👏👏</d><d p="59.13500,5,25,16776960,1525499252,0,c21d7c19,4512467164">可带精了！</d><d p="59.13500,5,25,16711935,1525499258,0,c21d7c19,4512467449">可带精了！</d><d p="59.13500,5,25,16777215,1525499268,0,c21d7c19,4512467932">可带精了！</d><d p="37.22200,1,25,16777215,1525519202,0,b71832e,4513403362">填词不错？这不就是原词。。。</d><d p="43.52400,1,25,16777215,1525520843,0,3db1b846,4513494698">7250！！！</d><d p="7.14600,1,25,16777215,1525521314,0,17d92084,4513521519">可耻的播放量</d><d p="66.78000,1,25,16777215,1525525974,0,d672771a,4513802377">火钳刘明 叶哥是真的优秀</d><d p="2.28100,1,25,16777215,1525525994,0,d672771a,4513803594">火钳刘明 叶哥优秀</d><d p="61.78000,1,25,16777215,1525529010,0,fedc062,4514010248">Jane•Ladge·Seder</d><d p="48.48300,1,25,16777215,1525534524,0,d83dc19,4514358209">强行很多很多</d><d p="38.06900,1,25,16777215,1525540181,0,6630230d,4514654045">隔句单押X1</d><d p="40.95700,1,25,16777215,1525566800,0,94214227,4515044167">火钳刘明</d><d p="0.65000,1,25,16777215,1525566997,0,20ed3daf,4515049096">如果大家再看到吟游诗人，请通过各种渠道联系面筋哥，帮帮面筋哥（吟游诗人已走丢）</d><d p="43.25800,1,25,16777215,1525569389,0,dfb8a350,4515119965">稳的很多</d><d p="48.70600,1,25,16777215,1525579560,0,46488adb,4515569052">求beat</d><d p="54.97900,1,25,16777215,1525580570,0,8ae73cb0,4515622970">简.拉基茨德</d><d p="18.10000,1,25,16777215,1525584156,0,869694b,4515830892">BGM：Forest Fires (Massappeals Remix)</d><d p="11.05000,1,25,16777215,1525590985,0,36dff635,4516191337">火钳刘明</d><d p="6.88700,1,25,16777215,1525593300,0,7081d5ab,4516301413">火钳刘明</d><d p="15.52300,1,25,16777215,1525593308,0,7081d5ab,4516301808">火钳刘明</d><d p="36.58800,1,25,16777215,1525598141,0,ccb870c7,4516534438">妙啊</d><d p="31.98900,1,25,16777215,1525601839,0,3aee2741,4516710466">很多很多</d><d p="37.22200,1,25,16777215,1525612675,0,4156589c,4517243145">他不是叫王宝强吗</d><d p="15.05700,4,18,16777215,1525660041,0,f32abdf7,4518303060">火钳刘明</d><d p="35.52700,1,25,16777215,1525682590,0,14b84552,4518901898">尿阿</d><d p="23.14600,1,25,16777215,1525682954,0,e79f742a,4518910664">左上王境泽</d><d p="52.42500,1,25,16777215,1525687089,0,ee63e640,4519032880">这两人互相嘲讽</d><d p="40.52000,1,25,16777215,1525690921,0,a9408a2a,4519181975">讲究</d><d p="10.13400,1,25,16777215,1525694513,0,970f5046,4519337995">新人太可怕了</d><d p="8.33900,1,25,16777215,1525694769,0,a7046db1,4519349048">叶哥？以为叫我233</d><d p="33.85300,1,25,16777215,1525703318,0,cf37c9c4,4519773166">👏👏👏👏👏👏👏👏👏👏👏👏👏👏👏👏</d><d p="23.68100,1,25,15138834,1525703452,0,bf997c28,4519780444">火钳刘明</d><d p="45.24100,1,25,15138834,1525703522,0,bf997c28,4519784323">牛逼</d><d p="42.34100,1,25,16777215,1525703584,0,4d9c1477,4519796275">我作为淮滨人 以前竟然没注意到面筋哥</d><d p="38.47500,1,25,15138834,1525705754,0,988e59,4519941241">单句双押X4</d><d p="41.49300,4,25,15138834,1525705770,0,988e59,4519942009">单句双押X5</d><d p="15.40700,1,25,16777215,1525708453,0,62320253,4520076501">火钳刘明</d><d p="48.25500,1,25,16777215,1525755885,0,ed25cb88,4520819854">很多很多</d><d p="18.56000,1,25,16777215,1525840445,0,ec9a439c,4522941015">火钳刘明</d><d p="52.20700,1,25,16777215,1525847393,0,89ef8f17,4523162986">吟游诗人</d><d p="13.23900,1,25,16777215,1525851305,0,5bf22684,4523240722">很多很多</d><d p="31.21100,1,25,16777215,1525862582,0,7e3ce810,4523890253">1。5倍更加</d><d p="52.70300,1,25,16777215,1525862736,0,7ed7e201,4523895888">rap这次是rap</d><d p="13.05400,1,25,16777215,1525867825,0,2096e2b6,4524094568">已找到诗人</d><d p="19.71200,1,25,16777215,1525876494,0,62906277,4524474534">加油</d><d p="38.46600,1,25,16777215,1525927222,0,2b065d4d,4525331903">很多很多</d><d p="20.30500,1,25,16777215,1525928137,0,40d87a2,4525367698">火钳刘明</d><d p="37.18100,1,25,16777215,1525930082,0,9005c87d,4525437034">亿万填词</d><d p="28.42500,1,25,16777215,1525945352,0,77834199,4525775333">妙</d><d p="22.57900,1,25,16777215,1525957768,0,bcf90c42,4526246930">火钳刘明</d><d p="32.62900,1,25,16777215,1525968778,0,66c3dcd1,4526797671">火钳刘明</d><d p="39.38800,1,25,16777215,1526107530,0,5bf7d171,4530651337">单压</d><d p="13.88000,1,25,16777215,1526298609,0,95fc1b57,4536980747">666</d><d p="60.36800,1,25,16777215,1526537932,0,d04ad40,4542555296">可带精了</d><d p="25.04200,1,25,14811775,1526732953,0,d04ad40,4548596557">好湿好湿</d><d p="40.58300,1,25,16777215,1526738927,0,ed8d67d4,4548933836">没有弹幕?</d><d p="16.89300,1,25,16777215,1526995591,0,de878f89,4556483982">火钳刘明</d><d p="42.03000,1,25,16777215,1527145679,0,7c2da980,4559923329">妙啊</d><d p="39.02600,1,25,16777215,1527344999,0,cdaf254b,106338394832898">火钳刘明</d><d p="59.94700,1,25,16777215,1527345020,0,cdaf254b,106349351927810">66666666666</d><d p="63.54000,1,25,16777215,1527345023,0,cdaf254b,106351243034626">6666666666</d><d p="15.14400,1,25,16777215,1527550961,0,3a45aeae,214321643126786">火钳刘明</d><d p="33.72700,1,25,16777215,1527701886,0,bb7802af,293449957900290">跟着节奏甩臀</d><d p="60.69900,1,25,16777215,1528601274,0,4a4abe87,764988334538752">淳，简，菈季池</d><d p="49.57500,1,25,16777215,1530354207,0,78d38aed,1684030082252800">1.25</d><d p="33.37600,1,25,16777215,1531913307,0,60ae80f3,2501447281278980">战术偷瞄</d><d p="23.43600,1,25,16777215,1536844666,0,7e319ede,5086899814793220">纯· 简 ·拉基·次德</d><d p="0.12900,1,25,16777215,1540895770,0,776360f8,7210845117349888">标准开头</d><d p="4.74300,1,25,16777215,1542685098,0,7203cdde,8148968353562624">开始我的节奏变得有点乱</d><d p="4.74300,4,25,16711680,1542685131,0,7203cdde,8148985585860608">开始我的节奏变得有点乱</d><d p="0.84000,7,36,16777215,1544079793,0,4b67c2f7,8880190172692480">[0,0,"1-1",4.5,"火钳留名","60","360",0,0,"1000","200",1,"\"Microsoft YaHei\"",1]</d><d p="14.95500,1,25,16777215,1545541076,0,f3c82285,9646323033178114">@吴亦凡 进来学说唱</d><d p="27.37400,1,25,16777215,1545541088,0,f3c82285,9646329530155010">@吴亦凡 进来挨打</d></i>