<?xml version="1.0" encoding="UTF-8"?><i><chatserver>chat.bilibili.com</chatserver><chatid>66815736</chatid><mission>0</mission><maxlimit>500</maxlimit><state>0</state><real_name>0</real_name><source>e-r</source><d p="9.08600,1,25,16777215,1544621613,0,9650ed0c,9164259713351680">我卡了？</d><d p="67.96500,1,25,16777215,1544707781,0,30da18b0,9209436537618432">嘛耶</d><d p="74.27000,1,25,16777215,1544707787,0,30da18b0,9209439833292800">舒服</d><d p="14.96000,1,25,16777215,1546154585,0,629c782,9967978473324544">黑了14秒的屏</d></i>